ocr/__init__.py
ocr/correct.py
ocr/cropimage.py
ocr/extract.py
ocr/utils.py
ocr/classifiers/__init__.py
ocr/classifiers/base.py
ocr/classifiers/knn.py
ocr/classifiers/mlp.py
ocr_testbed-0.0.1.dist-info/DESCRIPTION.rst
ocr_testbed-0.0.1.dist-info/METADATA
ocr_testbed-0.0.1.dist-info/RECORD
ocr_testbed-0.0.1.dist-info/WHEEL
ocr_testbed-0.0.1.dist-info/entry_points.txt
ocr_testbed-0.0.1.dist-info/metadata.json
ocr_testbed-0.0.1.dist-info/top_level.txt
scripts/__init__.py
scripts/knnextract.py
scripts/mlpextract.py
