Metadata-Version: 2.0
Name: ocr-testbed
Version: 0.0.1
Summary: OCR development and testing.
Home-page: https://github.com/PiJoules/ocr-project
Author: Leonard Chan
Author-email: lchan1994@yahoo.com
License: Unlicense
Keywords: ocr,knn,mlp
Platform: UNKNOWN
Classifier: Development Status :: 3 - Alpha
Requires-Dist: cv2 (==1.0)
Requires-Dist: matplotlib (==1.5.1)
Requires-Dist: numpy (==1.10.1)
Requires-Dist: scipy (==0.17.1)
